 {
    "base_config_file": "configs/rnd/ant_maze_resource/rnd/rnd.json",
    "experiment":{
        "tag": "rnd",
        "use_gpu": true,
        "seed": null,
        "base_log_dir": "/home/rl_shared/zhihaiwang/research/ICML_data/exploration_env_exps_fix_env/ant_corridor/rnd_v2/goal3_no_resource",
        "exp_prefix": "ant_corridor_rnd_goal3_no_resource"
    },
    "algorithm": {
        "name": "sac_rnd",
        "class": "RNDRLAlgorithm",
        "kwargs": {
            "num_epochs": 3000,
            "batch_size": 256,
            "num_eval_steps_per_epoch":8000,
            "num_train_loops_per_epoch": 1000,
            "num_expl_steps_per_train_loop": 1,
            "num_trains_per_train_loop": 1,
            "num_train_models_per_epoch": 1000,
            "max_path_length": 400,
            "train_model_freq": 25,
            "min_num_steps_before_training": 5000,
            "record_video_freq": 10,
            "silent": false
        }
    },
    "environment": [
        {
            "name": "expl_env",
            "class": "simple_env",
            "kwargs": {
                "env_name": "ant_corridor_env_3",
                "reward_scale": 1
            }
        },
        {
            "name": "eval_env",
            "class": "normalized_vector_env",
            "kwargs": {
                "env_name": "ant_corridor_env_3",
                "n_env":8,
                "reward_scale": 1
            }
        },
        {
            "name": "video_env",
            "class": "video_env",
            "kwargs": {
                "env_name": "ant_corridor_env_3"
            }
        }
    ]
}